rt_commission_dashboard/main.py
rt_commission_dashboard/core/config.py
rt_commission_dashboard/core/currency.py
rt_commission_dashboard/core/db_handler.py
rt_commission_dashboard/core/i18n.py
rt_commission_dashboard/core/paths.py
rt_commission_dashboard/core/supabase_handler.py
rt_commission_dashboard/locales/en.json
rt_commission_dashboard/locales/vi.json
rt_commission_dashboard/pages/affiliates.py
rt_commission_dashboard/pages/check_email.py
rt_commission_dashboard/pages/dashboard.py
rt_commission_dashboard/pages/email_confirmed.py
rt_commission_dashboard/pages/login.py
rt_commission_dashboard/pages/profiles.py
rt_commission_dashboard/pages/reports.py
rt_commission_dashboard/pages/settings.py
rt_commission_dashboard/pages/setup.py
rt_commission_dashboard/pages/signup.py
rt_commission_dashboard/pages/users.py
rt_commission_dashboard/ui/layout.py
rt_commission_dashboard/ui/theme.py
rt_commission_dashboard-1.2.27.dist-info/METADATA
rt_commission_dashboard-1.2.27.dist-info/WHEEL
rt_commission_dashboard-1.2.27.dist-info/entry_points.txt
rt_commission_dashboard-1.2.27.dist-info/licenses/LICENSE
rt_commission_dashboard-1.2.27.dist-info/RECORD
