Metadata-Version: 2.4
Name: rt-commission-dashboard
Version: 1.2.27
Summary: Multi-tier sales & commission tracking dashboard with hierarchical affiliate networks
Project-URL: Homepage, https://github.com/rtavytran/rt-commission-dashboard
Project-URL: Source, https://github.com/rtavytran/rt-commission-dashboard
Project-URL: Issues, https://github.com/rtavytran/rt-commission-dashboard/issues
Project-URL: Changelog, https://github.com/rtavytran/rt-commission-dashboard/blob/main/CHANGELOG.md
Author-email: RealTimeX Team <info@realtimex.ai>
License: Proprietary License
License-File: LICENSE
Keywords: affiliate,commission,dashboard,mlm,network-marketing,sales
Classifier: Development Status :: 4 - Beta
Classifier: Intended Audience :: Developers
Classifier: Programming Language :: Python :: 3
Classifier: Programming Language :: Python :: 3.10
Classifier: Programming Language :: Python :: 3.11
Classifier: Programming Language :: Python :: 3.12
Classifier: Programming Language :: Python :: 3.13
Classifier: Topic :: Office/Business :: Financial
Requires-Python: >=3.10
Requires-Dist: faker>=20.0.0
Requires-Dist: nicegui>=1.4.0
Requires-Dist: pandas>=2.0.0
Requires-Dist: plotly>=5.0.0
Requires-Dist: python-dotenv>=1.0.0
Requires-Dist: pyyaml>=6.0.0
Requires-Dist: supabase>=2.0.0
